Metadata-Version: 1.2
Name: pytest-fabric
Version: 1.0.0
Summary: Provides test utilities to run fabric task tests by using docker containers
Home-page: http://github.com/efagerberg/pytest-fabric
Author: Evan Fagerberg
Author-email: adioevan@gmail.com
License: MIT
Keywords: fabric docker pytest python
Platform: UNKNOWN
Classifier: Development Status :: 5 - Production/Stable
Classifier: Intended Audience :: Developers
Classifier: Operating System :: OS Independent
Classifier: License :: OSI Approved :: MIT License
Classifier: Topic :: Software Development :: Libraries :: Python Modules
Classifier: Topic :: Software Development :: Testing
Classifier: Programming Language :: Python
Classifier: Programming Language :: Python :: 2
Classifier: Programming Language :: Python :: 2.7
Requires-Python: >=2.7, !=3.0.*, !=3.1.*, !=3.2.*, !=3.3.*
